salute_plugin_sentry/__init__.py
salute_plugin_sentry/main.py
salute_plugin_sentry-0.0.0.dist-info/METADATA
salute_plugin_sentry-0.0.0.dist-info/WHEEL
salute_plugin_sentry-0.0.0.dist-info/entry_points.txt
salute_plugin_sentry-0.0.0.dist-info/top_level.txt
salute_plugin_sentry-0.0.0.dist-info/RECORD
