Metadata-Version: 2.4
Name: salute_plugin_sentry
Version: 0.0.0
Summary: Adding sentry support for salute application
Requires-Python: >=3.13
Requires-Dist: build>=1.2.2.post1
Requires-Dist: python-decouple>=3.8
Requires-Dist: sanic>=25.3.0
Requires-Dist: sentry-sdk>=2.32.0
